{
    "success": true,
    "totalResults": 732360,
    "first": 1,
    "last": 6,
    "resultCount": 6,
    "results": [
        {
            "trilat": 49.29005867,
            "trilong": -123.0914066,
            "ssid": "o2DSL",
            "qos": 0,
            "transid": null,
            "firsttime": "2022-12-21T02:55:31.000Z",
            "lasttime": "2023-09-08T11:47:36.000Z",
            "lastupdt": "2023-09-08T11:47:36.000Z",
            "netid": "00:26:F3:87:CD:F3",
            "name": null,
            "type": "infra",
            "comment": null,
            "wep": "3",
            "bcninterval": null,
            "freenet": "?",
            "dhcp": "?",
            "paynet": "Y",
            "userfound": false,
            "channel": 1,
            "rcois": null,
            "encryption": "wpa3",
            "country": "ca",
            "region": "British Columbia",
            "road": "Centennial Road",
            "city": "Vancouver",
            "housenumber": null,
            "postalcode": "V6A"
        },
        {
            "trilat": 49.2825071,
            "trilong": -123.08885918,
            "ssid": "POS",
            "qos": 0,
            "transid": null,
            "firsttime": "2007-09-26T12:16:25.000Z",
            "lasttime": "2016-07-22T12:32:07.000Z",
            "lastupdt": "2016-07-22T12:32:07.000Z",
            "netid": "AE:AE:19:0A:EB:85",
            "name": null,
            "type": "infra",
            "comment": null,
            "wep": "N",
            "bcninterval": null,
            "freenet": "?",
            "dhcp": "?",
            "paynet": "Y",
            "userfound": false,
            "channel": 8,
            "rcois": null,
            "encryption": "none",
            "country": "ca",
            "region": "British Columbia",
            "road": "East Cordova Street",
            "city": "Vancouver",
            "housenumber": null,
            "postalcode": "V6A"
        },
        {
            "trilat": 49.27864378,
            "trilong": -123.08606722,
            "ssid": ".@ AIS SUPER WiFi",
            "qos": 1,
            "transid": null,
            "firsttime": "2020-12-07T01:38:46.000Z",
            "lasttime": "2024-06-17T10:06:00.000Z",
            "lastupdt": "2024-06-17T10:06:00.000Z",
            "netid": "CC:5D:4E:2B:62:9A",
            "name": null,
            "type": "infra",
            "comment": null,
            "wep": "W",
            "bcninterval": null,
            "freenet": "?",
            "dhcp": "?",
            "paynet": "Y",
            "userfound": false,
            "channel": 11,
            "rcois": null,
            "encryption": "wpa",
            "country": "ca",
            "region": "British Columbia",
            "road": "East Georgia Street",
            "city": "Vancouver",
            "housenumber": null,
            "postalcode": "V6A"
        },
        {
            "trilat": 49.27523827,
            "trilong": -123.08962892,
            "ssid": "FRITZ!Box 6490 Cable",
            "qos": 0,
            "transid": null,
            "firsttime": "2002-05-07T22:11:19.000Z",
            "lasttime": "2010-10-21T05:41:23.000Z",
            "lastupdt": "2010-10-21T05:41:23.000Z",
            "netid": "78:45:58:4A:13:D0",
            "name": null,
            "type": "infra",
            "comment": null,
            "wep": "2",
            "bcninterval": null,
            "freenet": "?",
            "dhcp": "?",
            "paynet": "Y",
            "userfound": false,
            "channel": 1,
            "rcois": null,
            "encryption": "wpa2",
            "country": "ca",
            "region": "British Columbia",
            "road": "Malkin Avenue",
            "city": "Vancouver",
            "housenumber": "645",
            "postalcode": "V6A"
        },
        {
            "trilat": 49.29481245,
            "trilong": -123.08258512,
            "ssid": "Iteris_vectorR000172542050",
            "qos": 0,
            "transid": null,
            "firsttime": "2019-06-14T01:44:26.000Z",
            "lasttime": "2023-11-05T00:37:56.000Z",
            "lastupdt": "2023-11-05T00:37:56.000Z",
            "netid": "70:4F:57:CC:A2:07",
            "name": null,
            "type": "infra",
            "comment": null,
            "wep": "3",
            "bcninterval": null,
            "freenet": "?",
            "dhcp": "?",
            "paynet": "Y",
            "userfound": false,
            "channel": 6,
            "rcois": null,
            "encryption": "wpa3",
            "country": "ca",
            "region": "British Columbia",
            "road": null,
            "city": "Vancouver",
            "housenumber": null,
            "postalcode": "V6A 1R5"
        },
        {
            "trilat": 49.2788785,
            "trilong": -123.0770229,
            "ssid": "FON_FREE_INTERNET",
            "qos": 1,
            "transid": null,
            "firsttime": "2013-10-20T11:29:31.000Z",
            "lasttime": "2015-06-23T08:04:23.000Z",
            "lastupdt": "2015-06-23T08:04:23.000Z",
            "netid": "F4:C1:14:9F:FD:1A",
            "name": null,
            "type": "ad-hoc",
            "comment": null,
            "wep": "2",
            "bcninterval": null,
            "freenet": "?",
            "dhcp": "?",
            "paynet": "Y",
            "userfound": false,
            "channel": 6,
            "rcois": null,
            "encryption": "wpa2",
            "country": "ca",
            "region": "British Columbia",
            "road": "Clark Drive",
            "city": "Vancouver",
            "housenumber": "696",
            "postalcode": "V5L"
        }
    ],
    "searchAfter": "4534838964",
    "search_after": 4534838964
}
